{
  "heading": "Impi Scouting - 2025 v1",
  "logo": "logo.png",
  "pages": [
    {
      "name": "Setup",
      "widgets": [
        {
          "name": "Scouter Name",
            "type": "text",
            "col": 1,
            "row" :1,
            "validation": {
              "comparison": "greater",
              "value": 0
          }
        },
        {
          "name":"My nono square",
          "type": "spacer",
          "height": 25
        },
        {
         "name": "Starting Position",
          "type": "dropdown",
          "col": 1,
          "row" :3,
          "options": [
            "1",
            "2",
            "3"
          ]
        },
        {
          "name":"Space",
          "type": "spacer",
          "height": 15
        },
        {
          "type": "picture",
          "file": "field_numbers.png",
          "colspan": 2,
          "row" :5
        }
      ]
    },
    {
      "name": "Autonomous",
      "widgets": [
        {
          "name": "Left Starting Zone",
          "type": "checkbox",
          "col":3
        },
        {
          "type": "spacer",
          "height": 20
        },
        {
          "name": "Remove Algae",
          "type": "heading",
          "prefix": "Auto",
          "row": 3,
          "col": 3,
          "align": "left"
        },
        {
          "name": "Reef Low",
          "type": "spinbox",
          "prefix": "AutoAlgaePickup",
          "row": 3,
          "col": 4
        },
        {
          "name": "Reef High",
          "type": "spinbox",
          "prefix": "AutoAlgaePickup",
          "row": 4,
          "col": 4
        },
        {
          "name": "Scoring Algae",
          "type": "heading",
          "row": 5,
          "col":3
        },
        {
          "name": "Net",
          "type": "spinbox",
          "prefix": "Auto",
          "col": 4,
          "row": 5
        },
        {
          "name": "Proccesor",
          "type": "spinbox",
          "prefix": "Auto",
          "col": 4,
          "row" :6
        },
        {
          "name": "Scoring Coral",
          "type": "heading",
          "col": 3,
          "row" :7
        },
        {
          "name": "L1 Coral",
          "type": "spinbox",
          "prefix": "Auto",
          "row": 7,
          "col": 4
        },
        {
          "name": "L2 Coral",
          "type": "spinbox",
          "prefix": "Auto",
          "row": 8,
          "col": 4
        },
        {
          "name": "L3 Coral",
          "type": "spinbox",
          "prefix": "Auto",
          "col": 4,
          "row" :9
        },
        {
          "name": "L4 Coral",
          "type": "spinbox",
          "prefix": "Auto",
          "col": 4,
          "row": 10
        },
        {
          "name": "Coral Pick-up",
          "type": "heading",
          "col": 3,
          "row" :11
        },
        {
          "name": "Ground",
          "type": "checkbox",
          "prefix": "AutoCoralPickup",
          "col": 4,
          "row": 11
        },
        {
          "name": "HP Station",
          "type": "checkbox",
          "prefix": "AutoCoralPickup",
          "col": 4,
          "row": 12
        }
      ]
    },


    {
      "name": "Teleop",
      "widgets": [
        {
          "name": "Algae Pick-up",
          "type": "heading",
          "align": "center",
          "col": 3,
          "row":2
        },
        {
          "name": "Ground",
          "type": "spinbox",
          "prefix": "TeleopAlgaePickup",
          "col": 4,
          "row": 2
        },
        {
          "name": "Reef Low",
          "type": "spinbox",
          "prefix": "TeleopAlgaePickup",
          "row": 3,
          "col": 4
        },
        {
          "name": "Reef High",
          "type": "spinbox",
          "prefix": "TeleopAlgaePickup",
          "row": 4,
          "col": 4
        },
        {
          "name": "Coral Pick-up",
          "type": "heading",
          "row": 5,
          "col": 3,
          "align": "center"
        },
        {
          "name": "Ground",
          "type": "spinbox",
          "prefix": "TeleopCoralPickup",
          "col": 4,
          "row": 5
        },
        {
          "name": "HP Station",
          "type": "spinbox",
          "prefix": "TeleopCoralPickup",
          "row": 6,
          "col": 4
        },

        {
          "name": "Algae Scored",
          "type": "heading",
          "row": 8,
          "col": 3
        },
        {
          "name": "Net",
          "type": "spinbox",
          "prefix": "Teleop",
          "col": 4,
          "row": 8
        },
        {
          "name": "Proccesor",
          "type": "spinbox",
          "prefix": "Teleop",
          "row": 9,
          "col": 4
        },
        {
          "name": "Coral Scored",
          "type": "heading",
          "col": 3,
          "row": 10
        },
        {
          "name": "L1 Coral",
          "type": "spinbox",
          "prefix": "Teleop",
          "col": 4,
          "row": 10
        },
        {
          "name": "L2 Coral",
          "type": "spinbox",
          "prefix": "Teleop",
          "row": 11,
          "col": 4
        },
        {
          "name": "L3 Coral",
          "type": "spinbox",
          "prefix": "Teleop",
          "col": 4,
          "row": 12
        },
        {
          "name": "L4 Coral",
          "type": "spinbox",
          "prefix": "Teleop",
          "row": 13,
          "col": 4
        },
        {
          "name":"My nono square",
          "type": "spacer",
          "height": 15
        },
        {
          "name": "Dropped Corals",
          "type": "spinbox",
          "col": 4,
          "row" :15,
          "align": "center"
        }
      ]
    },
    {
      "name": "Endgame",
      "widgets": [
        {
          "name": "End Location",
          "type": "dropdown",
          "prefix": "Climb",
          "options": [
            "None",
            "Parked",
            "Shallow",
            "Deep"
          ],
          "col": 1,
          "row" :1

        },
        {
          "name":"Spacer1",
          "type": "spacer",
          "height": 5
        },
        {
          "name": "Failed Climb",
          "type": "checkbox",
          "col": 1,
          "row" :4
        },
        {
          "name":"Spacer2",
          "type": "spacer",
          "height": 15
        },
        {
          "name": "Robot Position",
          "type": "dropdown",
          "prefix": "Endgame",
          "options": [
            "1",
            "2",
            "3",
            "None"
          ],
          "col": 1,
          "row" :7
        },
        {
          "name":"Spacer3",
          "type": "spacer",
          "height": 10
        },
        {
          "type": "picture",
          "file": "barge_numbers.png",
          "colspan": 2,
          "row" :9
        }
      ]
    }
  ]
}
